README.txt
setup.cfg
setup.py
django_proxylist.egg-info/PKG-INFO
django_proxylist.egg-info/SOURCES.txt
django_proxylist.egg-info/dependency_links.txt
django_proxylist.egg-info/not-zip-safe
django_proxylist.egg-info/requires.txt
django_proxylist.egg-info/top_level.txt
proxylist/__init__.py
proxylist/admin.py
proxylist/models.py
proxylist/tasks.py
proxylist/tests.py
proxylist/urls.py
proxylist/views.py
proxylist/management/__init__.py
proxylist/management/commands/__init__.py
proxylist/management/commands/check_proxies.py
proxylist/management/commands/update_proxies.py