Metadata-Version: 1.1
Name: django-proxylist
Version: 0.1.0
Summary: Proxy-list management application for Django
Home-page: UNKNOWN
Author: Roberto Abdelkader Martínez Pérez
Author-email: robertomartinezp@gmail.com
License: GPL
Keywords: django proxylist
Platform: UNKNOWN
Classifier: Development Status :: 3 - Alpha
Classifier: Environment :: Console
Classifier: Environment :: Web Environment
Classifier: Framework :: Django
Classifier: License :: OSI Approved :: GNU General Public License v3 (GPLv3)
Classifier: Programming Language :: Python
Classifier: Topic :: Internet :: Proxy Servers
